<?xml version="1.0" encoding="utf-8"?>
<odoo>

    <data>
        <record id="cpm_odoo.project_workflows_list_view_tree" model="ir.ui.view">
            <field name="name">cpm_odoo.project_workflows_list.view.tree</field>
            <field name="model">cpm_odoo.planning_workflow</field>
            <field name="arch" type="xml">
                <tree string="" create="True" edit="True" delete="True">
                    <field name="planning_id" string="Planning ID"></field>
                    <field name="name" string="Name"></field>
                    <field name="task_count" string="Task Count"></field>
                    <field name="draft_task_count" string="Draft Count"></field>
                    <field name="planning_id" domain="[('id','=',context.get('project_id',1))]"></field>
                </tree>
            </field>
        </record>
    </data>
</odoo>